pytabulator/__init__.py
pytabulator/_table_options_dc.py
pytabulator/_table_options_pydantic.py
pytabulator/_types.py
pytabulator/_utils.py
pytabulator/experimental.py
pytabulator/shiny_bindings.py
pytabulator/srcjs/get-tabulator.sh
pytabulator/srcjs/tabulator-bindings.js
pytabulator/srcjs/tabulator.min.css
pytabulator/srcjs/tabulator.min.js
pytabulator/srcjs/tabulator_bootstrap3.min.css
pytabulator/srcjs/tabulator_bootstrap4.min.css
pytabulator/srcjs/tabulator_bootstrap5.min.css
pytabulator/srcjs/tabulator_bulma.min.css
pytabulator/srcjs/tabulator_materialize.min.css
pytabulator/srcjs/tabulator_midnight.min.css
pytabulator/srcjs/tabulator_modern.min.css
pytabulator/srcjs/tabulator_semanticui.min.css
pytabulator/srcjs/tabulator_simple.min.css
pytabulator/srcjs/tabulator_site.min.css
pytabulator/tabulator.py
pytabulator/tabulator_context.py
pytabulator/theme.py
pytabulator/ui.py
pytabulator/utils.py
pytabulator-0.2.5.dist-info/LICENSE
pytabulator-0.2.5.dist-info/METADATA
pytabulator-0.2.5.dist-info/WHEEL
pytabulator-0.2.5.dist-info/RECORD
