Metadata-Version: 2.1
Name: pytabulator
Version: 0.2.5
Summary: Shiny bindings for Tabulator JS
License: MIT
Author: Stefan Kuethe
Author-email: stefan.kuethe@eoda.de
Requires-Python: >=3.9,<4.0
Classifier: License :: OSI Approved :: MIT License
Classifier: Programming Language :: Python :: 3
Classifier: Programming Language :: Python :: 3.9
Classifier: Programming Language :: Python :: 3.10
Classifier: Programming Language :: Python :: 3.11
Provides-Extra: all
Provides-Extra: pydantic
Requires-Dist: pandas
Requires-Dist: pydantic (>=2.6.1,<3.0.0) ; extra == "all" or extra == "pydantic"
Requires-Dist: shiny (>=0.7.0)
